[
    {
        "id": 67724755,
        "node_id": "MDEwOlJlcG9zaXRvcnk2NzcyNDc1NQ==",
        "name": "gnatstudio",
        "full_name": "AdaCore/gnatstudio",
        "private": false,
        "owner": {
            "login": "AdaCore",
            "id": 7767877,
            "node_id": "MDEyOk9yZ2FuaXphdGlvbjc3Njc4Nzc=",
            "avatar_url": "https://avatars.githubusercontent.com/u/7767877?v=4",
            "gravatar_id": "",
            "url": "https://api.github.com/users/AdaCore",
            "html_url": "https://github.com/AdaCore",
            "followers_url": "https://api.github.com/users/AdaCore/followers",
            "following_url": "https://api.github.com/users/AdaCore/following{/other_user}",
            "gists_url": "https://api.github.com/users/AdaCore/gists{/gist_id}",
            "starred_url": "https://api.github.com/users/AdaCore/starred{/owner}{/repo}",
            "subscriptions_url": "https://api.github.com/users/AdaCore/subscriptions",
            "organizations_url": "https://api.github.com/users/AdaCore/orgs",
            "repos_url": "https://api.github.com/users/AdaCore/repos",
            "events_url": "https://api.github.com/users/AdaCore/events{/privacy}",
            "received_events_url": "https://api.github.com/users/AdaCore/received_events",
            "type": "Organization",
            "site_admin": false
        },
        "html_url": "https://github.com/AdaCore/gnatstudio",
        "description": "GNAT Studio is a powerful and lightweight IDE for Ada and SPARK.",
        "fork": false,
        "url": "https://api.github.com/repos/AdaCore/gnatstudio",
        "forks_url": "https://api.github.com/repos/AdaCore/gnatstudio/forks",
        "keys_url": "https://api.github.com/repos/AdaCore/gnatstudio/keys{/key_id}",
        "collaborators_url": "https://api.github.com/repos/AdaCore/gnatstudio/collaborators{/collaborator}",
        "teams_url": "https://api.github.com/repos/AdaCore/gnatstudio/teams",
        "hooks_url": "https://api.github.com/repos/AdaCore/gnatstudio/hooks",
        "issue_events_url": "https://api.github.com/repos/AdaCore/gnatstudio/issues/events{/number}",
        "events_url": "https://api.github.com/repos/AdaCore/gnatstudio/events",
        "assignees_url": "https://api.github.com/repos/AdaCore/gnatstudio/assignees{/user}",
        "branches_url": "https://api.github.com/repos/AdaCore/gnatstudio/branches{/branch}",
        "tags_url": "https://api.github.com/repos/AdaCore/gnatstudio/tags",
        "blobs_url": "https://api.github.com/repos/AdaCore/gnatstudio/git/blobs{/sha}",
        "git_tags_url": "https://api.github.com/repos/AdaCore/gnatstudio/git/tags{/sha}",
        "git_refs_url": "https://api.github.com/repos/AdaCore/gnatstudio/git/refs{/sha}",
        "trees_url": "https://api.github.com/repos/AdaCore/gnatstudio/git/trees{/sha}",
        "statuses_url": "https://api.github.com/repos/AdaCore/gnatstudio/statuses/{sha}",
        "languages_url": "https://api.github.com/repos/AdaCore/gnatstudio/languages",
        "stargazers_url": "https://api.github.com/repos/AdaCore/gnatstudio/stargazers",
        "contributors_url": "https://api.github.com/repos/AdaCore/gnatstudio/contributors",
        "subscribers_url": "https://api.github.com/repos/AdaCore/gnatstudio/subscribers",
        "subscription_url": "https://api.github.com/repos/AdaCore/gnatstudio/subscription",
        "commits_url": "https://api.github.com/repos/AdaCore/gnatstudio/commits{/sha}",
        "git_commits_url": "https://api.github.com/repos/AdaCore/gnatstudio/git/commits{/sha}",
        "comments_url": "https://api.github.com/repos/AdaCore/gnatstudio/comments{/number}",
        "issue_comment_url": "https://api.github.com/repos/AdaCore/gnatstudio/issues/comments{/number}",
        "contents_url": "https://api.github.com/repos/AdaCore/gnatstudio/contents/{+path}",
        "compare_url": "https://api.github.com/repos/AdaCore/gnatstudio/compare/{base}...{head}",
        "merges_url": "https://api.github.com/repos/AdaCore/gnatstudio/merges",
        "archive_url": "https://api.github.com/repos/AdaCore/gnatstudio/{archive_format}{/ref}",
        "downloads_url": "https://api.github.com/repos/AdaCore/gnatstudio/downloads",
        "issues_url": "https://api.github.com/repos/AdaCore/gnatstudio/issues{/number}",
        "pulls_url": "https://api.github.com/repos/AdaCore/gnatstudio/pulls{/number}",
        "milestones_url": "https://api.github.com/repos/AdaCore/gnatstudio/milestones{/number}",
        "notifications_url": "https://api.github.com/repos/AdaCore/gnatstudio/notifications{?since,all,participating}",
        "labels_url": "https://api.github.com/repos/AdaCore/gnatstudio/labels{/name}",
        "releases_url": "https://api.github.com/repos/AdaCore/gnatstudio/releases{/id}",
        "deployments_url": "https://api.github.com/repos/AdaCore/gnatstudio/deployments",
        "created_at": "2016-09-08T17:22:47Z",
        "updated_at": "2024-04-15T05:25:55Z",
        "pushed_at": "2024-04-19T10:04:58Z",
        "git_url": "git://github.com/AdaCore/gnatstudio.git",
        "ssh_url": "git@github.com:AdaCore/gnatstudio.git",
        "clone_url": "https://github.com/AdaCore/gnatstudio.git",
        "svn_url": "https://github.com/AdaCore/gnatstudio",
        "homepage": "",
        "size": 140492,
        "stargazers_count": 374,
        "watchers_count": 374,
        "language": "Ada",
        "has_issues": true,
        "has_projects": true,
        "has_downloads": true,
        "has_wiki": false,
        "has_pages": false,
        "has_discussions": false,
        "forks_count": 53,
        "mirror_url": null,
        "archived": false,
        "disabled": false,
        "open_issues_count": 42,
        "license": null,
        "allow_forking": true,
        "is_template": false,
        "web_commit_signoff_required": false,
        "topics": [],
        "visibility": "public",
        "forks": 53,
        "open_issues": 42,
        "watchers": 374,
        "default_branch": "master",
        "permissions": {
            "admin": false,
            "maintain": false,
            "push": false,
            "triage": false,
            "pull": true
        },
        "score": 1.0
    },
    {
        "id": 361585920,
        "node_id": "MDEwOlJlcG9zaXRvcnkzNjE1ODU5MjA=",
        "name": "septum",
        "full_name": "pyjarrett/septum",
        "private": false,
        "owner": {
            "login": "pyjarrett",
            "id": 5159849,
            "node_id": "MDQ6VXNlcjUxNTk4NDk=",
            "avatar_url": "https://avatars.githubusercontent.com/u/5159849?v=4",
            "gravatar_id": "",
            "url": "https://api.github.com/users/pyjarrett",
            "html_url": "https://github.com/pyjarrett",
            "followers_url": "https://api.github.com/users/pyjarrett/followers",
            "following_url": "https://api.github.com/users/pyjarrett/following{/other_user}",
            "gists_url": "https://api.github.com/users/pyjarrett/gists{/gist_id}",
            "starred_url": "https://api.github.com/users/pyjarrett/starred{/owner}{/repo}",
            "subscriptions_url": "https://api.github.com/users/pyjarrett/subscriptions",
            "organizations_url": "https://api.github.com/users/pyjarrett/orgs",
            "repos_url": "https://api.github.com/users/pyjarrett/repos",
            "events_url": "https://api.github.com/users/pyjarrett/events{/privacy}",
            "received_events_url": "https://api.github.com/users/pyjarrett/received_events",
            "type": "User",
            "site_admin": false
        },
        "html_url": "https://github.com/pyjarrett/septum",
        "description": "Context-based code search tool",
        "fork": false,
        "url": "https://api.github.com/repos/pyjarrett/septum",
        "forks_url": "https://api.github.com/repos/pyjarrett/septum/forks",
        "keys_url": "https://api.github.com/repos/pyjarrett/septum/keys{/key_id}",
        "collaborators_url": "https://api.github.com/repos/pyjarrett/septum/collaborators{/collaborator}",
        "teams_url": "https://api.github.com/repos/pyjarrett/septum/teams",
        "hooks_url": "https://api.github.com/repos/pyjarrett/septum/hooks",
        "issue_events_url": "https://api.github.com/repos/pyjarrett/septum/issues/events{/number}",
        "events_url": "https://api.github.com/repos/pyjarrett/septum/events",
        "assignees_url": "https://api.github.com/repos/pyjarrett/septum/assignees{/user}",
        "branches_url": "https://api.github.com/repos/pyjarrett/septum/branches{/branch}",
        "tags_url": "https://api.github.com/repos/pyjarrett/septum/tags",
        "blobs_url": "https://api.github.com/repos/pyjarrett/septum/git/blobs{/sha}",
        "git_tags_url": "https://api.github.com/repos/pyjarrett/septum/git/tags{/sha}",
        "git_refs_url": "https://api.github.com/repos/pyjarrett/septum/git/refs{/sha}",
        "trees_url": "https://api.github.com/repos/pyjarrett/septum/git/trees{/sha}",
        "statuses_url": "https://api.github.com/repos/pyjarrett/septum/statuses/{sha}",
        "languages_url": "https://api.github.com/repos/pyjarrett/septum/languages",
        "stargazers_url": "https://api.github.com/repos/pyjarrett/septum/stargazers",
        "contributors_url": "https://api.github.com/repos/pyjarrett/septum/contributors",
        "subscribers_url": "https://api.github.com/repos/pyjarrett/septum/subscribers",
        "subscription_url": "https://api.github.com/repos/pyjarrett/septum/subscription",
        "commits_url": "https://api.github.com/repos/pyjarrett/septum/commits{/sha}",
        "git_commits_url": "https://api.github.com/repos/pyjarrett/septum/git/commits{/sha}",
        "comments_url": "https://api.github.com/repos/pyjarrett/septum/comments{/number}",
        "issue_comment_url": "https://api.github.com/repos/pyjarrett/septum/issues/comments{/number}",
        "contents_url": "https://api.github.com/repos/pyjarrett/septum/contents/{+path}",
        "compare_url": "https://api.github.com/repos/pyjarrett/septum/compare/{base}...{head}",
        "merges_url": "https://api.github.com/repos/pyjarrett/septum/merges",
        "archive_url": "https://api.github.com/repos/pyjarrett/septum/{archive_format}{/ref}",
        "downloads_url": "https://api.github.com/repos/pyjarrett/septum/downloads",
        "issues_url": "https://api.github.com/repos/pyjarrett/septum/issues{/number}",
        "pulls_url": "https://api.github.com/repos/pyjarrett/septum/pulls{/number}",
        "milestones_url": "https://api.github.com/repos/pyjarrett/septum/milestones{/number}",
        "notifications_url": "https://api.github.com/repos/pyjarrett/septum/notifications{?since,all,participating}",
        "labels_url": "https://api.github.com/repos/pyjarrett/septum/labels{/name}",
        "releases_url": "https://api.github.com/repos/pyjarrett/septum/releases{/id}",
        "deployments_url": "https://api.github.com/repos/pyjarrett/septum/deployments",
        "created_at": "2021-04-26T01:50:20Z",
        "updated_at": "2024-04-16T14:35:17Z",
        "pushed_at": "2024-03-08T05:47:16Z",
        "git_url": "git://github.com/pyjarrett/septum.git",
        "ssh_url": "git@github.com:pyjarrett/septum.git",
        "clone_url": "https://github.com/pyjarrett/septum.git",
        "svn_url": "https://github.com/pyjarrett/septum",
        "homepage": "",
        "size": 414,
        "stargazers_count": 368,
        "watchers_count": 368,
        "language": "Ada",
        "has_issues": true,
        "has_projects": true,
        "has_downloads": true,
        "has_wiki": true,
        "has_pages": false,
        "has_discussions": false,
        "forks_count": 6,
        "mirror_url": null,
        "archived": false,
        "disabled": false,
        "open_issues_count": 14,
        "license": {
            "key": "apache-2.0",
            "name": "Apache License 2.0",
            "spdx_id": "Apache-2.0",
            "url": "https://api.github.com/licenses/apache-2.0",
            "node_id": "MDc6TGljZW5zZTI="
        },
        "allow_forking": true,
        "is_template": false,
        "web_commit_signoff_required": false,
        "topics": [
            "ada",
            "grep",
            "grep-like",
            "grep-search",
            "search-in-text",
            "septum",
            "text"
        ],
        "visibility": "public",
        "forks": 6,
        "open_issues": 14,
        "watchers": 368,
        "default_branch": "main",
        "permissions": {
            "admin": false,
            "maintain": false,
            "push": false,
            "triage": false,
            "pull": true
        },
        "score": 1.0
    },
    {
        "id": 769253713,
        "node_id": "R_kgDOLdnhUQ",
        "name": "eepers",
        "full_name": "tsoding/eepers",
        "private": false,
        "owner": {
            "login": "tsoding",
            "id": 18597647,
            "node_id": "MDEyOk9yZ2FuaXphdGlvbjE4NTk3NjQ3",
            "avatar_url": "https://avatars.githubusercontent.com/u/18597647?v=4",
            "gravatar_id": "",
            "url": "https://api.github.com/users/tsoding",
            "html_url": "https://github.com/tsoding",
            "followers_url": "https://api.github.com/users/tsoding/followers",
            "following_url": "https://api.github.com/users/tsoding/following{/other_user}",
            "gists_url": "https://api.github.com/users/tsoding/gists{/gist_id}",
            "starred_url": "https://api.github.com/users/tsoding/starred{/owner}{/repo}",
            "subscriptions_url": "https://api.github.com/users/tsoding/subscriptions",
            "organizations_url": "https://api.github.com/users/tsoding/orgs",
            "repos_url": "https://api.github.com/users/tsoding/repos",
            "events_url": "https://api.github.com/users/tsoding/events{/privacy}",
            "received_events_url": "https://api.github.com/users/tsoding/received_events",
            "type": "Organization",
            "site_admin": false
        },
        "html_url": "https://github.com/tsoding/eepers",
        "description": "Simple Turn-based Game",
        "fork": false,
        "url": "https://api.github.com/repos/tsoding/eepers",
        "forks_url": "https://api.github.com/repos/tsoding/eepers/forks",
        "keys_url": "https://api.github.com/repos/tsoding/eepers/keys{/key_id}",
        "collaborators_url": "https://api.github.com/repos/tsoding/eepers/collaborators{/collaborator}",
        "teams_url": "https://api.github.com/repos/tsoding/eepers/teams",
        "hooks_url": "https://api.github.com/repos/tsoding/eepers/hooks",
        "issue_events_url": "https://api.github.com/repos/tsoding/eepers/issues/events{/number}",
        "events_url": "https://api.github.com/repos/tsoding/eepers/events",
        "assignees_url": "https://api.github.com/repos/tsoding/eepers/assignees{/user}",
        "branches_url": "https://api.github.com/repos/tsoding/eepers/branches{/branch}",
        "tags_url": "https://api.github.com/repos/tsoding/eepers/tags",
        "blobs_url": "https://api.github.com/repos/tsoding/eepers/git/blobs{/sha}",
        "git_tags_url": "https://api.github.com/repos/tsoding/eepers/git/tags{/sha}",
        "git_refs_url": "https://api.github.com/repos/tsoding/eepers/git/refs{/sha}",
        "trees_url": "https://api.github.com/repos/tsoding/eepers/git/trees{/sha}",
        "statuses_url": "https://api.github.com/repos/tsoding/eepers/statuses/{sha}",
        "languages_url": "https://api.github.com/repos/tsoding/eepers/languages",
        "stargazers_url": "https://api.github.com/repos/tsoding/eepers/stargazers",
        "contributors_url": "https://api.github.com/repos/tsoding/eepers/contributors",
        "subscribers_url": "https://api.github.com/repos/tsoding/eepers/subscribers",
        "subscription_url": "https://api.github.com/repos/tsoding/eepers/subscription",
        "commits_url": "https://api.github.com/repos/tsoding/eepers/commits{/sha}",
        "git_commits_url": "https://api.github.com/repos/tsoding/eepers/git/commits{/sha}",
        "comments_url": "https://api.github.com/repos/tsoding/eepers/comments{/number}",
        "issue_comment_url": "https://api.github.com/repos/tsoding/eepers/issues/comments{/number}",
        "contents_url": "https://api.github.com/repos/tsoding/eepers/contents/{+path}",
        "compare_url": "https://api.github.com/repos/tsoding/eepers/compare/{base}...{head}",
        "merges_url": "https://api.github.com/repos/tsoding/eepers/merges",
        "archive_url": "https://api.github.com/repos/tsoding/eepers/{archive_format}{/ref}",
        "downloads_url": "https://api.github.com/repos/tsoding/eepers/downloads",
        "issues_url": "https://api.github.com/repos/tsoding/eepers/issues{/number}",
        "pulls_url": "https://api.github.com/repos/tsoding/eepers/pulls{/number}",
        "milestones_url": "https://api.github.com/repos/tsoding/eepers/milestones{/number}",
        "notifications_url": "https://api.github.com/repos/tsoding/eepers/notifications{?since,all,participating}",
        "labels_url": "https://api.github.com/repos/tsoding/eepers/labels{/name}",
        "releases_url": "https://api.github.com/repos/tsoding/eepers/releases{/id}",
        "deployments_url": "https://api.github.com/repos/tsoding/eepers/deployments",
        "created_at": "2024-03-08T16:56:02Z",
        "updated_at": "2024-04-20T18:05:57Z",
        "pushed_at": "2024-04-05T11:36:33Z",
        "git_url": "git://github.com/tsoding/eepers.git",
        "ssh_url": "git@github.com:tsoding/eepers.git",
        "clone_url": "https://github.com/tsoding/eepers.git",
        "svn_url": "https://github.com/tsoding/eepers",
        "homepage": "",
        "size": 72831,
        "stargazers_count": 267,
        "watchers_count": 267,
        "language": "Ada",
        "has_issues": true,
        "has_projects": true,
        "has_downloads": true,
        "has_wiki": false,
        "has_pages": false,
        "has_discussions": false,
        "forks_count": 17,
        "mirror_url": null,
        "archived": false,
        "disabled": false,
        "open_issues_count": 6,
        "license": {
            "key": "mit",
            "name": "MIT License",
            "spdx_id": "MIT",
            "url": "https://api.github.com/licenses/mit",
            "node_id": "MDc6TGljZW5zZTEz"
        },
        "allow_forking": true,
        "is_template": false,
        "web_commit_signoff_required": false,
        "topics": [
            "ada",
            "game",
            "raylib",
            "turn-based"
        ],
        "visibility": "public",
        "forks": 17,
        "open_issues": 6,
        "watchers": 267,
        "default_branch": "main",
        "permissions": {
            "admin": false,
            "maintain": false,
            "push": false,
            "triage": false,
            "pull": true
        },
        "score": 1.0
    },
    {
        "id": 37367962,
        "node_id": "MDEwOlJlcG9zaXRvcnkzNzM2Nzk2Mg==",
        "name": "whitakers-words",
        "full_name": "mk270/whitakers-words",
        "private": false,
        "owner": {
            "login": "mk270",
            "id": 923403,
            "node_id": "MDQ6VXNlcjkyMzQwMw==",
            "avatar_url": "https://avatars.githubusercontent.com/u/923403?v=4",
            "gravatar_id": "",
            "url": "https://api.github.com/users/mk270",
            "html_url": "https://github.com/mk270",
            "followers_url": "https://api.github.com/users/mk270/followers",
            "following_url": "https://api.github.com/users/mk270/following{/other_user}",
            "gists_url": "https://api.github.com/users/mk270/gists{/gist_id}",
            "starred_url": "https://api.github.com/users/mk270/starred{/owner}{/repo}",
            "subscriptions_url": "https://api.github.com/users/mk270/subscriptions",
            "organizations_url": "https://api.github.com/users/mk270/orgs",
            "repos_url": "https://api.github.com/users/mk270/repos",
            "events_url": "https://api.github.com/users/mk270/events{/privacy}",
            "received_events_url": "https://api.github.com/users/mk270/received_events",
            "type": "User",
            "site_admin": false
        },
        "html_url": "https://github.com/mk270/whitakers-words",
        "description": "William Whitaker's WORDS, a Latin dictionary",
        "fork": false,
        "url": "https://api.github.com/repos/mk270/whitakers-words",
        "forks_url": "https://api.github.com/repos/mk270/whitakers-words/forks",
        "keys_url": "https://api.github.com/repos/mk270/whitakers-words/keys{/key_id}",
        "collaborators_url": "https://api.github.com/repos/mk270/whitakers-words/collaborators{/collaborator}",
        "teams_url": "https://api.github.com/repos/mk270/whitakers-words/teams",
        "hooks_url": "https://api.github.com/repos/mk270/whitakers-words/hooks",
        "issue_events_url": "https://api.github.com/repos/mk270/whitakers-words/issues/events{/number}",
        "events_url": "https://api.github.com/repos/mk270/whitakers-words/events",
        "assignees_url": "https://api.github.com/repos/mk270/whitakers-words/assignees{/user}",
        "branches_url": "https://api.github.com/repos/mk270/whitakers-words/branches{/branch}",
        "tags_url": "https://api.github.com/repos/mk270/whitakers-words/tags",
        "blobs_url": "https://api.github.com/repos/mk270/whitakers-words/git/blobs{/sha}",
        "git_tags_url": "https://api.github.com/repos/mk270/whitakers-words/git/tags{/sha}",
        "git_refs_url": "https://api.github.com/repos/mk270/whitakers-words/git/refs{/sha}",
        "trees_url": "https://api.github.com/repos/mk270/whitakers-words/git/trees{/sha}",
        "statuses_url": "https://api.github.com/repos/mk270/whitakers-words/statuses/{sha}",
        "languages_url": "https://api.github.com/repos/mk270/whitakers-words/languages",
        "stargazers_url": "https://api.github.com/repos/mk270/whitakers-words/stargazers",
        "contributors_url": "https://api.github.com/repos/mk270/whitakers-words/contributors",
        "subscribers_url": "https://api.github.com/repos/mk270/whitakers-words/subscribers",
        "subscription_url": "https://api.github.com/repos/mk270/whitakers-words/subscription",
        "commits_url": "https://api.github.com/repos/mk270/whitakers-words/commits{/sha}",
        "git_commits_url": "https://api.github.com/repos/mk270/whitakers-words/git/commits{/sha}",
        "comments_url": "https://api.github.com/repos/mk270/whitakers-words/comments{/number}",
        "issue_comment_url": "https://api.github.com/repos/mk270/whitakers-words/issues/comments{/number}",
        "contents_url": "https://api.github.com/repos/mk270/whitakers-words/contents/{+path}",
        "compare_url": "https://api.github.com/repos/mk270/whitakers-words/compare/{base}...{head}",
        "merges_url": "https://api.github.com/repos/mk270/whitakers-words/merges",
        "archive_url": "https://api.github.com/repos/mk270/whitakers-words/{archive_format}{/ref}",
        "downloads_url": "https://api.github.com/repos/mk270/whitakers-words/downloads",
        "issues_url": "https://api.github.com/repos/mk270/whitakers-words/issues{/number}",
        "pulls_url": "https://api.github.com/repos/mk270/whitakers-words/pulls{/number}",
        "milestones_url": "https://api.github.com/repos/mk270/whitakers-words/milestones{/number}",
        "notifications_url": "https://api.github.com/repos/mk270/whitakers-words/notifications{?since,all,participating}",
        "labels_url": "https://api.github.com/repos/mk270/whitakers-words/labels{/name}",
        "releases_url": "https://api.github.com/repos/mk270/whitakers-words/releases{/id}",
        "deployments_url": "https://api.github.com/repos/mk270/whitakers-words/deployments",
        "created_at": "2015-06-13T10:49:01Z",
        "updated_at": "2024-04-12T15:37:16Z",
        "pushed_at": "2023-07-03T14:52:07Z",
        "git_url": "git://github.com/mk270/whitakers-words.git",
        "ssh_url": "git@github.com:mk270/whitakers-words.git",
        "clone_url": "https://github.com/mk270/whitakers-words.git",
        "svn_url": "https://github.com/mk270/whitakers-words",
        "homepage": "http://mk270.github.io/whitakers-words/",
        "size": 7234,
        "stargazers_count": 263,
        "watchers_count": 263,
        "language": "Ada",
        "has_issues": true,
        "has_projects": true,
        "has_downloads": true,
        "has_wiki": true,
        "has_pages": true,
        "has_discussions": false,
        "forks_count": 54,
        "mirror_url": null,
        "archived": false,
        "disabled": false,
        "open_issues_count": 46,
        "license": {
            "key": "other",
            "name": "Other",
            "spdx_id": "NOASSERTION",
            "url": null,
            "node_id": "MDc6TGljZW5zZTA="
        },
        "allow_forking": true,
        "is_template": false,
        "web_commit_signoff_required": false,
        "topics": [],
        "visibility": "public",
        "forks": 54,
        "open_issues": 46,
        "watchers": 263,
        "default_branch": "master",
        "permissions": {
            "admin": false,
            "maintain": false,
            "push": false,
            "triage": false,
            "pull": true
        },
        "score": 1.0
    },
    {
        "id": 124904219,
        "node_id": "MDEwOlJlcG9zaXRvcnkxMjQ5MDQyMTk=",
        "name": "alire",
        "full_name": "alire-project/alire",
        "private": false,
        "owner": {
            "login": "alire-project",
            "id": 30287851,
            "node_id": "MDEyOk9yZ2FuaXphdGlvbjMwMjg3ODUx",
            "avatar_url": "https://avatars.githubusercontent.com/u/30287851?v=4",
            "gravatar_id": "",
            "url": "https://api.github.com/users/alire-project",
            "html_url": "https://github.com/alire-project",
            "followers_url": "https://api.github.com/users/alire-project/followers",
            "following_url": "https://api.github.com/users/alire-project/following{/other_user}",
            "gists_url": "https://api.github.com/users/alire-project/gists{/gist_id}",
            "starred_url": "https://api.github.com/users/alire-project/starred{/owner}{/repo}",
            "subscriptions_url": "https://api.github.com/users/alire-project/subscriptions",
            "organizations_url": "https://api.github.com/users/alire-project/orgs",
            "repos_url": "https://api.github.com/users/alire-project/repos",
            "events_url": "https://api.github.com/users/alire-project/events{/privacy}",
            "received_events_url": "https://api.github.com/users/alire-project/received_events",
            "type": "Organization",
            "site_admin": false
        },
        "html_url": "https://github.com/alire-project/alire",
        "description": "Command-line tool from the Alire project and supporting library",
        "fork": false,
        "url": "https://api.github.com/repos/alire-project/alire",
        "forks_url": "https://api.github.com/repos/alire-project/alire/forks",
        "keys_url": "https://api.github.com/repos/alire-project/alire/keys{/key_id}",
        "collaborators_url": "https://api.github.com/repos/alire-project/alire/collaborators{/collaborator}",
        "teams_url": "https://api.github.com/repos/alire-project/alire/teams",
        "hooks_url": "https://api.github.com/repos/alire-project/alire/hooks",
        "issue_events_url": "https://api.github.com/repos/alire-project/alire/issues/events{/number}",
        "events_url": "https://api.github.com/repos/alire-project/alire/events",
        "assignees_url": "https://api.github.com/repos/alire-project/alire/assignees{/user}",
        "branches_url": "https://api.github.com/repos/alire-project/alire/branches{/branch}",
        "tags_url": "https://api.github.com/repos/alire-project/alire/tags",
        "blobs_url": "https://api.github.com/repos/alire-project/alire/git/blobs{/sha}",
        "git_tags_url": "https://api.github.com/repos/alire-project/alire/git/tags{/sha}",
        "git_refs_url": "https://api.github.com/repos/alire-project/alire/git/refs{/sha}",
        "trees_url": "https://api.github.com/repos/alire-project/alire/git/trees{/sha}",
        "statuses_url": "https://api.github.com/repos/alire-project/alire/statuses/{sha}",
        "languages_url": "https://api.github.com/repos/alire-project/alire/languages",
        "stargazers_url": "https://api.github.com/repos/alire-project/alire/stargazers",
        "contributors_url": "https://api.github.com/repos/alire-project/alire/contributors",
        "subscribers_url": "https://api.github.com/repos/alire-project/alire/subscribers",
        "subscription_url": "https://api.github.com/repos/alire-project/alire/subscription",
        "commits_url": "https://api.github.com/repos/alire-project/alire/commits{/sha}",
        "git_commits_url": "https://api.github.com/repos/alire-project/alire/git/commits{/sha}",
        "comments_url": "https://api.github.com/repos/alire-project/alire/comments{/number}",
        "issue_comment_url": "https://api.github.com/repos/alire-project/alire/issues/comments{/number}",
        "contents_url": "https://api.github.com/repos/alire-project/alire/contents/{+path}",
        "compare_url": "https://api.github.com/repos/alire-project/alire/compare/{base}...{head}",
        "merges_url": "https://api.github.com/repos/alire-project/alire/merges",
        "archive_url": "https://api.github.com/repos/alire-project/alire/{archive_format}{/ref}",
        "downloads_url": "https://api.github.com/repos/alire-project/alire/downloads",
        "issues_url": "https://api.github.com/repos/alire-project/alire/issues{/number}",
        "pulls_url": "https://api.github.com/repos/alire-project/alire/pulls{/number}",
        "milestones_url": "https://api.github.com/repos/alire-project/alire/milestones{/number}",
        "notifications_url": "https://api.github.com/repos/alire-project/alire/notifications{?since,all,participating}",
        "labels_url": "https://api.github.com/repos/alire-project/alire/labels{/name}",
        "releases_url": "https://api.github.com/repos/alire-project/alire/releases{/id}",
        "deployments_url": "https://api.github.com/repos/alire-project/alire/deployments",
        "created_at": "2018-03-12T14:45:18Z",
        "updated_at": "2024-04-14T11:18:34Z",
        "pushed_at": "2024-03-26T00:10:43Z",
        "git_url": "git://github.com/alire-project/alire.git",
        "ssh_url": "git@github.com:alire-project/alire.git",
        "clone_url": "https://github.com/alire-project/alire.git",
        "svn_url": "https://github.com/alire-project/alire",
        "homepage": "",
        "size": 5948,
        "stargazers_count": 255,
        "watchers_count": 255,
        "language": "Ada",
        "has_issues": true,
        "has_projects": true,
        "has_downloads": true,
        "has_wiki": true,
        "has_pages": false,
        "has_discussions": true,
        "forks_count": 46,
        "mirror_url": null,
        "archived": false,
        "disabled": false,
        "open_issues_count": 266,
        "license": {
            "key": "gpl-3.0",
            "name": "GNU General Public License v3.0",
            "spdx_id": "GPL-3.0",
            "url": "https://api.github.com/licenses/gpl-3.0",
            "node_id": "MDc6TGljZW5zZTk="
        },
        "allow_forking": true,
        "is_template": false,
        "web_commit_signoff_required": false,
        "topics": [
            "ada",
            "ada-2012",
            "package-management",
            "package-manager",
            "package-manager-tool",
            "reproducible-builds"
        ],
        "visibility": "public",
        "forks": 46,
        "open_issues": 266,
        "watchers": 255,
        "default_branch": "master",
        "permissions": {
            "admin": false,
            "maintain": false,
            "push": false,
            "triage": false,
            "pull": true
        },
        "score": 1.0
    }
]