[
    {
        "name": "axoloti-contrib",
        "description": "User contributed objects and patches for Axoloti",
        "languages": {
            "NetLinx": 1146766,
            "C": 428035,
            "C++": 221770,
            "HTML": 524
        }
    },
    {
        "name": "amx-util-library",
        "description": "Various useful NetLinx include files and modules",
        "languages": {
            "NetLinx": 284726
        }
    },
    {
        "name": "netlinx-common-libraries",
        "description": "Lightweight native libraries for augmenting the base functionality of the NetLinx language used for programming AMX NetLinx integrated controllers.",
        "languages": {
            "NetLinx": 103693
        }
    },
    {
        "name": "AMX",
        "description": "AMX home automation using NetLinx with generalizations for easier reuse on many projects. Configuration files allow modules to be reused without code changes. I currently use this project in two homes with only the configuration files being different. Similarly, the same TP4 GUI front-ends (iPad and iPhone with iRidium app) work in multiple locations without changes.",
        "languages": {
            "NetLinx": 536750,
            "XSLT": 2566
        }
    },
    {
        "name": "jsmn",
        "description": "A minimalistic JSON parser for NetLinx",
        "languages": {
            "NetLinx": 12619
        }
    },
    {
        "name": "Axoloti-Block",
        "description": "Axoloti hardware synth for the Roli Blocks system",
        "languages": {
            "NetLinx": 10167
        }
    },
    {
        "name": "netlinx-libJSON",
        "description": "A Netlinx library for validating, parsing, modifying, and creating JSON data",
        "languages": {
            "NetLinx": 50838
        }
    },
    {
        "name": "sublime-netlinx",
        "description": "Develop AMX NetLinx projects in the Sublime Text editor.",
        "languages": {
            "NetLinx": 7950,
            "Python": 4052,
            "JavaScript": 1648
        }
    },
    {
        "name": "netlinx-global-code",
        "description": "Cross project Modules and Includes for AMX Netlinx programming",
        "languages": {
            "NetLinx": 3062246
        }
    },
    {
        "name": "http",
        "description": "A lightweight HTTP library for working with web services in NetLinx",
        "languages": {
            "NetLinx": 17082
        }
    },
    {
        "name": "AMX-IP-Socket-Manager",
        "description": "AMX NetLinx IP Socket Manager",
        "languages": {
            "NetLinx": 11256
        }
    },
    {
        "name": "mongiloti",
        "description": "A synthesizer built from Axoloti and Teensy",
        "languages": {
            "NetLinx": 16306,
            "C++": 10267,
            "C": 5308
        }
    },
    {
        "name": "AMX_ATEM",
        "description": null,
        "languages": {
            "NetLinx": 43249
        }
    },
    {
        "name": "amx-lib-redis",
        "description": "A Redis database client for AMX's NetLinx programming language.",
        "languages": {
            "NetLinx": 77935,
            "NetLinx+ERB": 1856,
            "Ruby": 575
        }
    },
    {
        "name": "AMX",
        "description": "AMX Code Snippets",
        "languages": {
            "NetLinx": 1197379,
            "C": 1163
        }
    },
    {
        "name": "Teach-Cliste-Home-Control",
        "description": "With the rapid advancement of network connected technology, home automation is a growing market. \u00a0  The objective of the project is to design and build a control interface that will bring together the control of light, heat, audio and video in a simple yet intuitive user interface. Despite there being applications available to control the majority of connected home devices, few combine this into a single interface.  The project will involve designing a front end interface which will run on an Apple iPad. The application will communicate with the different elements of the system using AMX. A working prototype will demonstrate a range of communication methods including infra-red, RS232 and IP.  Home automation technologies simplify living, but also helps monitor energy efficiency and security. The project will incorporate a popular lighting control system, the Phillips Hue, which will result in significant energy savings for the user.\u00a0  After conducting market research, it was noted that entertainment is a key element of home automation systems. With this in mind, the project will incorporate control of audio and video sources including Apple TV, Blu-ray player and much more.\u00a0  The control system will be developed on a NetLinx NX-3200 integrated controller and programmed in AMX NetLinx code. The user interface will be developed utilising TPDesign and hosted on an iPad by TPControl.",
        "languages": {
            "NetLinx": 93508,
            "HTML": 69102
        }
    },
    {
        "name": "netlinx-project-boilerplate",
        "description": "Boilerplate for rapid spinup of AMX NetLinx distributed control system projects",
        "languages": {
            "NetLinx": 8161,
            "Shell": 510
        }
    },
    {
        "name": "Netlinx-UPnP-control-point",
        "description": "UPnP control point for Netlinx AMX",
        "languages": {
            "NetLinx": 63559
        }
    },
    {
        "name": "amx-modero-library",
        "description": "API, Control, and Listener Include Files for AMX Modero Panels",
        "languages": {
            "NetLinx": 262316
        }
    },
    {
        "name": "amx-device-library",
        "description": "NetLinx Include Library Files for AMX Device Control",
        "languages": {
            "NetLinx": 38879
        }
    },
    {
        "name": "amx-lib-bss",
        "description": "BSS Soundweb London API for AMX NetLinx",
        "languages": {
            "NetLinx": 75516
        }
    },
    {
        "name": "NetLinxTutorial",
        "description": "Learn the NetLinx programming language with this quick tutorial",
        "languages": {
            "NetLinx": 7090
        }
    },
    {
        "name": "axo-patches",
        "description": "code repo for my axoloti",
        "languages": {
            "NetLinx": 750737,
            "C": 15427,
            "C++": 13875,
            "HTML": 442
        }
    },
    {
        "name": "amx",
        "description": "Helpful AMX modules I've developed on various projects",
        "languages": {
            "NetLinx": 38873
        }
    },
    {
        "name": "amx-snmp-library",
        "description": "Netlinx SNMP Manager module and RMS monitor module",
        "languages": {
            "NetLinx": 200582
        }
    },
    {
        "name": "BoxeeBox",
        "description": "AMX Control module for Boxee Box and XBMC",
        "languages": {
            "NetLinx": 29930
        }
    },
    {
        "name": "AMX-smart-home",
        "description": null,
        "languages": {
            "NetLinx": 178088
        }
    },
    {
        "name": "ACiS",
        "description": null,
        "languages": {
            "NetLinx": 2879367,
            "VHDL": 1617714,
            "Verilog": 1049252,
            "SystemVerilog": 996713,
            "C": 816962,
            "Python": 663404,
            "Jupyter Notebook": 628356,
            "Tcl": 448970,
            "C++": 231609,
            "HTML": 139719,
            "Makefile": 125948,
            "Shell": 77336,
            "Perl": 63446,
            "LLVM": 51022,
            "Assembly": 36587,
            "Stata": 2907,
            "JavaScript": 2579,
            "CSS": 1820,
            "Pascal": 1136,
            "Forth": 552
        }
    },
    {
        "name": "hohum-axoctrl",
        "description": "Axoctrl objects and patches",
        "languages": {
            "NetLinx": 63564
        }
    },
    {
        "name": "commandfusion",
        "description": "Automatically exported from code.google.com/p/commandfusion",
        "languages": {
            "NetLinx": 81042,
            "Visual Basic": 61904,
            "Python": 17552
        }
    },
    {
        "name": "SynthGuitar",
        "description": "An Axoloti-based guitar-style synthesizer",
        "languages": {
            "NetLinx": 8068
        }
    },
    {
        "name": "AMX_Enova_Novara_Web",
        "description": "Simple coding example for an AMX Enova, with Novara keypads, and a primitive Web server",
        "languages": {
            "NetLinx": 25453
        }
    },
    {
        "name": "amx-dvx-library",
        "description": "API, Control, and Listener Include Files for AMX Enova DVX Switchers",
        "languages": {
            "NetLinx": 252405
        }
    },
    {
        "name": "AMX-Includes",
        "description": "NetLinx Libraries to extend functionality",
        "languages": {
            "NetLinx": 40320
        }
    },
    {
        "name": "NAVFoundation.Amx",
        "description": "A collection of libraries for NetLinx software development",
        "languages": {
            "NetLinx": 560808,
            "C": 10274,
            "PowerShell": 8206,
            "Shell": 1276
        }
    },
    {
        "name": "amx-dxlink-library",
        "description": "API, Control, and Listener Include Files for AMX DXLink devices (receivers, transmitters, wall-plates)",
        "languages": {
            "NetLinx": 77028
        }
    },
    {
        "name": "LNC-AMX",
        "description": null,
        "languages": {
            "NetLinx": 944715
        }
    },
    {
        "name": "rcMDL",
        "description": "A netlinx module template for quickly bootstrapping device drivers.",
        "languages": {
            "NetLinx": 78826
        }
    },
    {
        "name": "audio-system-netlinx",
        "description": "Audio System for Netlinx studio using TPDesign to create a design for the system.",
        "languages": {
            "NetLinx": 109536
        }
    },
    {
        "name": "oslinx",
        "description": "Automatically exported from code.google.com/p/oslinx",
        "languages": {
            "NetLinx": 22990
        }
    },
    {
        "name": "amx",
        "description": null,
        "languages": {
            "NetLinx": 2549213,
            "HTML": 25
        }
    },
    {
        "name": "AMX-Netlinx-Extron_DMP64",
        "description": "Netlinx Module for Extron DMP64",
        "languages": {
            "NetLinx": 38354
        }
    },
    {
        "name": "AMX-Practical",
        "description": "practical stuff",
        "languages": {
            "NetLinx": 125175
        }
    },
    {
        "name": "TinyHTTPLib",
        "description": "A tiny NetLinx native HTTP library based loosely on 'gHttp (HttpImpl)', http lib' & 'cURL'.",
        "languages": {
            "NetLinx": 14590
        }
    },
    {
        "name": "AMX-netlinx-ip-connections",
        "description": null,
        "languages": {
            "NetLinx": 5294
        }
    },
    {
        "name": "HydroDyn",
        "description": "Hydrodynamics routines for offshore wind turbine analysis",
        "languages": {
            "NetLinx": 49077695,
            "Groff": 10674648,
            "Fortran": 5434635,
            "MATLAB": 125191,
            "Batchfile": 13594,
            "Makefile": 11198
        }
    },
    {
        "name": "House-AMX",
        "description": "Amx stuff for my house install",
        "languages": {
            "NetLinx": 968831
        }
    },
    {
        "name": "instaments",
        "description": "Instant Instruments for your Axoloti",
        "languages": {
            "NetLinx": 42289
        }
    },
    {
        "name": "axi-art",
        "description": "Procgen line art to plot on an AxiDraw",
        "languages": {
            "NetLinx": 388589,
            "Python": 46904
        }
    },
    {
        "name": "AMX-IP-Manager",
        "description": "Little framework to get IP connection managed in AMX NetLinx Studio",
        "languages": {
            "NetLinx": 53655
        }
    },
    {
        "name": "Integrate-2015-Collaborative-Learning-Space",
        "description": "AMX System demonstrating a Collaborative Learning Space at Integrate 2015 in Melbourne",
        "languages": {
            "NetLinx": 16411
        }
    },
    {
        "name": "avSystem_workspace",
        "description": null,
        "languages": {
            "NetLinx": 323955
        }
    },
    {
        "name": "amx-au-mel-boardroom",
        "description": "AMX Australia Melbourne Office Boardroom Control System",
        "languages": {
            "NetLinx": 402434
        }
    },
    {
        "name": "Projet-Industriel",
        "description": null,
        "languages": {
            "NetLinx": 127052,
            "JavaScript": 72626,
            "CSS": 16976,
            "PHP": 8765,
            "Hack": 1655
        }
    },
    {
        "name": "axoloti",
        "description": "My patches (mostly remixes of community patches)",
        "languages": {
            "NetLinx": 4131
        }
    },
    {
        "name": "av-1619",
        "description": "AMX 1619",
        "languages": {
            "NetLinx": 166376
        }
    },
    {
        "name": "kgi-project",
        "description": null,
        "languages": {
            "NetLinx": 13893361,
            "Verilog": 3831213,
            "C": 1408873,
            "Tcl": 508062,
            "Python": 370171,
            "SystemVerilog": 191433,
            "VHDL": 156372,
            "Makefile": 103705,
            "C++": 87026,
            "C#": 80208,
            "Shell": 47190,
            "Coq": 14966,
            "HTML": 6339,
            "Pascal": 3124,
            "JavaScript": 2579,
            "CSS": 1820
        }
    },
    {
        "name": "AMX-netlinx-notes",
        "description": null,
        "languages": {
            "NetLinx": 13695
        }
    },
    {
        "name": "jv-axoloti-objects",
        "description": "Custom Axoloti Objects",
        "languages": {
            "NetLinx": 2370
        }
    },
    {
        "name": "NAVDatabase.Amx.PanasonicProjector",
        "description": "NetLinx module for Panasonic projectors",
        "languages": {
            "NetLinx": 37632,
            "PowerShell": 8103,
            "Shell": 1276
        }
    },
    {
        "name": "amx-test-suite",
        "description": null,
        "languages": {
            "NetLinx": 34881
        }
    },
    {
        "name": "roku-external-control",
        "description": "AMX NetLinx control module for Roku set top box",
        "languages": {
            "NetLinx": 17907
        }
    },
    {
        "name": "EBR",
        "description": null,
        "languages": {
            "NetLinx": 27012
        }
    },
    {
        "name": "integrate-2016-ui",
        "description": "User interfaces shown at Integrate 2016",
        "languages": {
            "NetLinx": 10122
        }
    },
    {
        "name": "AMX-Acendo-Vibe",
        "description": "Netlinx Module for AMX Acendo Vibe",
        "languages": {
            "NetLinx": 28890
        }
    },
    {
        "name": "otomis-ledix-collab",
        "description": null,
        "languages": {
            "NetLinx": 665354
        }
    },
    {
        "name": "NZ-Facilities-Integrate-SVSi-Demo-2015",
        "description": "SVSi video distribution including G5 Drag & Drop Feature demonstration. ",
        "languages": {
            "NetLinx": 12704
        }
    },
    {
        "name": "AMX",
        "description": null,
        "languages": {
            "NetLinx": 3860697
        }
    },
    {
        "name": "Hushbutton-PCI-AMX-Demo-Program",
        "description": null,
        "languages": {
            "NetLinx": 20472
        }
    },
    {
        "name": "axoloti-patches",
        "description": "patches for axoloti board",
        "languages": {
            "NetLinx": 13940,
            "Python": 322
        }
    },
    {
        "name": "NAVDatabase.Amx.PanasonicCamera",
        "description": "AMX NetLinx module for Panasonic cameras",
        "languages": {
            "NetLinx": 13586,
            "PowerShell": 8103,
            "Shell": 1276
        }
    },
    {
        "name": "Integrate-2015-Boardroom",
        "description": "AMX System demonstrating a Boardroom at Integrate 2015 in Melbourne",
        "languages": {
            "NetLinx": 311530
        }
    },
    {
        "name": "amx-home-automation",
        "description": null,
        "languages": {
            "NetLinx": 38375
        }
    },
    {
        "name": "Netlinx-Dictionary",
        "description": "Netlinx Implementation of Dictionary Data Structure",
        "languages": {
            "NetLinx": 9002
        }
    },
    {
        "name": "home_automation",
        "description": null,
        "languages": {
            "NetLinx": 79348
        }
    },
    {
        "name": "AMX-Test-Code",
        "description": "Example to quickly test pieces of code",
        "languages": {
            "NetLinx": 1790
        }
    },
    {
        "name": "0JGE5SPV6F",
        "description": "5610435a-287a-4aa8-b713-eecc05916c04",
        "languages": {
            "NetLinx": 38
        }
    },
    {
        "name": "NetLinx-VARIA-NFC",
        "description": null,
        "languages": {
            "NetLinx": 5961
        }
    },
    {
        "name": "NetLinx-FloatingPoint-Binary",
        "description": null,
        "languages": {
            "NetLinx": 7373
        }
    },
    {
        "name": "amx-lib-volume",
        "description": null,
        "languages": {
            "NetLinx": 109917,
            "Ruby": 5159
        }
    },
    {
        "name": "oslinx",
        "description": "Automatically exported from code.google.com/p/oslinx",
        "languages": {
            "NetLinx": 22990
        }
    },
    {
        "name": "axoloti_synth",
        "description": null,
        "languages": {
            "NetLinx": 10336
        }
    },
    {
        "name": "test_CI",
        "description": "test windows CI to include netlinx studio build process in my netlinx project",
        "languages": {
            "NetLinx": 177408
        }
    },
    {
        "name": "axotest",
        "description": "Testing Axoloti objects and patches",
        "languages": {
            "NetLinx": 51905,
            "Objective-C": 16352,
            "Scilab": 1026
        }
    },
    {
        "name": "commandfusion",
        "description": "Automatically exported from code.google.com/p/commandfusion",
        "languages": {
            "NetLinx": 81042,
            "Visual Basic": 61904,
            "Python": 17552
        }
    },
    {
        "name": "ssb_axoloti",
        "description": "Source code for projects with the Axoloti microcontroler synth board.",
        "languages": {
            "NetLinx": 155409
        }
    },
    {
        "name": "axolib",
        "description": "My patches for Axoloti",
        "languages": {
            "NetLinx": 4162
        }
    },
    {
        "name": "AMX-Module-Template",
        "description": "NetLinx module to control IP or 232 devices",
        "languages": {
            "NetLinx": 29829
        }
    },
    {
        "name": "AMX-Project-Template",
        "description": "Project template for new Netlinx projects",
        "languages": {
            "NetLinx": 9034
        }
    },
    {
        "name": "NetlinxProgram",
        "description": null,
        "languages": {
            "NetLinx": 504156
        }
    },
    {
        "name": "Sound-system",
        "description": null,
        "languages": {
            "NetLinx": 109536
        }
    },
    {
        "name": "NAVDatabase.Amx.ExtronDMP",
        "description": "NetLinx module for Extron DMP range of DSP's",
        "languages": {
            "NetLinx": 97895,
            "PowerShell": 8103,
            "Shell": 1276
        }
    },
    {
        "name": "NAVDatabase.Amx.ShureMXA",
        "description": "NetLinx module for Shure MXA range of microphones",
        "languages": {
            "NetLinx": 12128,
            "PowerShell": 8103,
            "Shell": 1276
        }
    },
    {
        "name": "NAVDatabase.Amx.PanasonicDisplay",
        "description": "NetLinx module for Panasonic displays",
        "languages": {
            "NetLinx": 35637,
            "PowerShell": 8103,
            "Shell": 1276
        }
    },
    {
        "name": "NetLinx-STRUCTURE-Bainary",
        "description": null,
        "languages": {
            "NetLinx": 6651
        }
    },
    {
        "name": "jurassicamx",
        "description": null,
        "languages": {
            "NetLinx": 119290
        }
    },
    {
        "name": "AMX",
        "description": "AMX Code Snippets",
        "languages": {
            "NetLinx": 271078
        }
    },
    {
        "name": "MITE_AMX_PANELS_CODE",
        "description": null,
        "languages": {
            "NetLinx": 94710
        }
    },
    {
        "name": "AMX_Proje",
        "description": null,
        "languages": {
            "NetLinx": 50276
        }
    },
    {
        "name": "AMX-netlinx-timelines",
        "description": "Timelines in NetLinx language",
        "languages": {
            "NetLinx": 2397
        }
    },
    {
        "name": "andorloti",
        "description": "My axoloti patches collection",
        "languages": {
            "NetLinx": 11221
        }
    },
    {
        "name": "amx-enzo-library",
        "description": "API, control and listener include files for AMX Enzo",
        "languages": {
            "NetLinx": 17352
        }
    },
    {
        "name": "avt-room-booking-2016",
        "description": "Room booking panel interface deployed at avt offices",
        "languages": {
            "NetLinx": 6575
        }
    },
    {
        "name": "amx-echo",
        "description": "AMX module for integrating AMX NetLinx masters with Echo360 EchoSystem Server.",
        "languages": {
            "NetLinx": 296477
        }
    },
    {
        "name": "optoma-projector-module",
        "description": "Netlinx module for Optoma Projector",
        "languages": {
            "NetLinx": 18346
        }
    },
    {
        "name": "axoloti_patches",
        "description": "Some patches for the Axoloti Core platform",
        "languages": {
            "NetLinx": 8446
        }
    },
    {
        "name": "AMX-Analog-Way-VIO-4k",
        "description": "A module for control an Analog Way VIO 4k with AMX/Netlinx",
        "languages": {
            "NetLinx": 7418
        }
    },
    {
        "name": "NAVDatabase.Amx.ExtronSSP",
        "description": "NetLinx module for Extron SSP-200",
        "languages": {
            "NetLinx": 28949,
            "PowerShell": 8103,
            "Shell": 1276
        }
    },
    {
        "name": "calnen",
        "description": "AMX Cal Nen a Sant Pere de Vilamajor 9Lluis COLL)",
        "languages": {
            "NetLinx": 206912
        }
    },
    {
        "name": "auditoria-amx",
        "description": null,
        "languages": {
            "NetLinx": 1892
        }
    },
    {
        "name": "netlinx-dali",
        "description": "Module for AMX controller.  Helvar DALI light control.",
        "languages": {
            "NetLinx": 31399
        }
    },
    {
        "name": "AMX-netlinx",
        "description": null,
        "languages": {
            "NetLinx": 16824
        }
    },
    {
        "name": "NetLinx-SelectSort",
        "description": null,
        "languages": {
            "NetLinx": 4680
        }
    },
    {
        "name": "---my-features---",
        "description": "tp features",
        "languages": {
            "NetLinx": 4691
        }
    },
    {
        "name": "axoloti-patches",
        "description": null,
        "languages": {
            "NetLinx": 22388
        }
    },
    {
        "name": "chaste-simulations",
        "description": null,
        "languages": {
            "NetLinx": 12788551,
            "C++": 798055,
            "Python": 29695,
            "CMake": 7108
        }
    },
    {
        "name": "4OpFMSynth",
        "description": "Polyphonic, 4 Operator, Frequency Modulation Synthesizer",
        "languages": {
            "NetLinx": 33870
        }
    },
    {
        "name": "axoloti_fma",
        "description": "Patches and objects, and maybe some code, for the axoloti audio development board. www.axoloti.com",
        "languages": {
            "NetLinx": 3332
        }
    },
    {
        "name": "MyCondPannels",
        "description": "AMX module to communicate with MyCond thermostat pannels. Includes test interface and example of implementation",
        "languages": {
            "NetLinx": 35926
        }
    },
    {
        "name": "av-607",
        "description": "AMX 607 Classroom",
        "languages": {
            "NetLinx": 251322
        }
    },
    {
        "name": "amx-lib-bss",
        "description": null,
        "languages": {
            "NetLinx": 75516
        }
    },
    {
        "name": "amx-skigin-lahta",
        "description": null,
        "languages": {
            "NetLinx": 1258447
        }
    },
    {
        "name": "AMX_Massio_Test",
        "description": null,
        "languages": {
            "NetLinx": 3575
        }
    },
    {
        "name": "netlinx-csv",
        "description": "Parse CSV in AMX Netlinx",
        "languages": {
            "NetLinx": 9784
        }
    },
    {
        "name": "amx-encoder-library",
        "description": "API, Control, and Listener Include Files for AMX H.264 Encoder",
        "languages": {
            "NetLinx": 27272
        }
    },
    {
        "name": "AMX-Generic-Modules",
        "description": "Generic modules for controlling the most typical devices",
        "languages": {
            "NetLinx": 48564
        }
    },
    {
        "name": "netlinx_pid",
        "description": "pid controller for netlinx controllers",
        "languages": {
            "NetLinx": 3553
        }
    },
    {
        "name": "NetLinx-hash",
        "description": null,
        "languages": {
            "NetLinx": 32495
        }
    },
    {
        "name": "NAVDatabase.Amx.EpsonESC-VP21Business",
        "description": "AMX NetLinx module for Epson ESC/VP21 Business projectors",
        "languages": {
            "NetLinx": 30932,
            "PowerShell": 8103,
            "Shell": 1276
        }
    },
    {
        "name": "axoloti_home",
        "description": null,
        "languages": {
            "NetLinx": 177333
        }
    },
    {
        "name": "amx_bsd",
        "description": "The netlinx code for positec show room's center controller",
        "languages": {
            "NetLinx": 146474
        }
    },
    {
        "name": "AMX_Practical",
        "description": "Created Repository",
        "languages": {
            "NetLinx": 689936
        }
    },
    {
        "name": "amx-snmp-library",
        "description": null,
        "languages": {
            "NetLinx": 200582
        }
    },
    {
        "name": "AMX-By-Harman",
        "description": "Training Files & NetLinx Coding Examples",
        "languages": {
            "NetLinx": 1178259
        }
    },
    {
        "name": "NAVDatabase.Amx.LightwareLW3",
        "description": "NetLinx module for Lightware LW3 compatible devices",
        "languages": {
            "NetLinx": 21274,
            "PowerShell": 8103,
            "Shell": 1276
        }
    },
    {
        "name": "axoloti_pastitas",
        "description": null,
        "languages": {
            "NetLinx": 18041
        }
    },
    {
        "name": "q-hotel-katowice",
        "description": "q-hotel-katowice",
        "languages": {
            "NetLinx": 115172
        }
    },
    {
        "name": "Salem-College",
        "description": "First Commit to Create Repo",
        "languages": {
            "NetLinx": 264147
        }
    },
    {
        "name": "integrate-2015-Cafe",
        "description": "AMX system running in the \"Cafe\" at Integrate 2015 in Melbourne",
        "languages": {
            "NetLinx": 3592
        }
    },
    {
        "name": "MTSU-1006",
        "description": null,
        "languages": {
            "NetLinx": 1123981
        }
    },
    {
        "name": "Axoloti-Patches",
        "description": "What I found on the laptop. Beginning to clean up",
        "languages": {
            "NetLinx": 665775,
            "C++": 147959,
            "C": 63470
        }
    },
    {
        "name": "smartRoom",
        "description": null,
        "languages": {
            "NetLinx": 294573
        }
    },
    {
        "name": "AMX-CYP-Matrix-Control",
        "description": "This AMX module allow control of the CYP AV Matrix",
        "languages": {
            "NetLinx": 10269
        }
    }
]